filewatchdog/__init__.py
filewatchdog-0.1.5.dist-info/LICENSE
filewatchdog-0.1.5.dist-info/METADATA
filewatchdog-0.1.5.dist-info/WHEEL
filewatchdog-0.1.5.dist-info/RECORD
