Metadata-Version: 2.1
Name: filewatchdog
Version: 0.1.5
Summary: Runs Python functions once a certain file is created or modified.
License: MIT
Author: BeginnerSC
Requires-Python: >=3.9,<4.0
Classifier: License :: OSI Approved :: MIT License
Classifier: Programming Language :: Python :: 3
Classifier: Programming Language :: Python :: 3.9
Classifier: Programming Language :: Python :: 3.10
Classifier: Programming Language :: Python :: 3.11
Classifier: Programming Language :: Python :: 3.12
Requires-Dist: schedule (>=1.2.1,<2.0.0)
